KekikTaban/__init__.py
KekikTaban/konsolTaban.py
KekikTaban-0.5.0.dist-info/LICENSE
KekikTaban-0.5.0.dist-info/METADATA
KekikTaban-0.5.0.dist-info/WHEEL
KekikTaban-0.5.0.dist-info/top_level.txt
KekikTaban-0.5.0.dist-info/RECORD
